 [{
		"gender": "male",
		"name": {
			"title": "Monsieur",
			"first": "Aron",
			"last": "Richard"
		},
		"nat": "CH"
	}, {
		"gender": "female",
		"name": {
			"title": "Ms",
			"first": "Anastasija",
			"last": "Šakić"
		},
		"nat": "RS"
	}, {
		"gender": "male",
		"name": {
			"title": "Mr",
			"first": "Chara",
			"last": "Berezenko"
		},
		"nat": "UA"
	}, {
		"gender": "male",
		"name": {
			"title": "Mr",
			"first": "Isaac",
			"last": "Rey"
		},
		"nat": "FR"
	}, {
		"gender": "female",
		"name": {
			"title": "Mrs",
			"first": "Jill",
			"last": "Watson"
		},
		"nat": "US"
	}, {
		"gender": "male",
		"name": {
			"title": "Mr",
			"first": "Petar",
			"last": "Rump"
		},
		"nat": "DE"
	}, {
		"gender": "male",
		"name": {
			"title": "Mr",
			"first": "Vedat",
			"last": "Erdoğan"
		},
		"nat": "TR"
	}, {
		"gender": "male",
		"name": {
			"title": "Mr",
			"first": "Felix",
			"last": "Escalante"
		},
		"nat": "MX"
	}, {
		"gender": "female",
		"name": {
			"title": "Ms",
			"first": "Laura",
			"last": "Rasmussen"
		},
		"nat": "DK"
	}, {
		"gender": "female",
		"name": {
			"title": "Miss",
			"first": "Kristen",
			"last": "Bennett"
		},
		"nat": "US"
	}, {
		"gender": "male",
		"name": {
			"title": "Mr",
			"first": "Arine",
			"last": "da Luz"
		},
		"nat": "BR"
	}, {
		"gender": "male",
		"name": {
			"title": "Mr",
			"first": "Amando",
			"last": "Gillissen"
		},
		"nat": "NL"
	}, {
		"gender": "male",
		"name": {
			"title": "Mr",
			"first": "Zachary",
			"last": "Roy"
		},
		"nat": "CA"
	}, {
		"gender": "female",
		"name": {
			"title": "Mrs",
			"first": "Wilma",
			"last": "Danner"
		},
		"nat": "DE"
	}, {
		"gender": "female",
		"name": {
			"title": "Mrs",
			"first": "Elisa",
			"last": "Vega"
		},
		"nat": "ES"
	}, {
		"gender": "female",
		"name": {
			"title": "Mrs",
			"first": "Mihaela",
			"last": "Radojičić"
		},
		"nat": "RS"
	}, {
		"gender": "female",
		"name": {
			"title": "Miss",
			"first": "Alexis",
			"last": "Lam"
		},
		"nat": "CA"
	}, {
		"gender": "female",
		"name": {
			"title": "Ms",
			"first": "Paulina",
			"last": "Ocasio"
		},
		"nat": "MX"
	}, {
		"gender": "female",
		"name": {
			"title": "Ms",
			"first": "Louella",
			"last": "Allen"
		},
		"nat": "AU"
	}, {
		"gender": "female",
		"name": {
			"title": "Mademoiselle",
			"first": "Gabriela",
			"last": "Rodriguez"
		},
		"nat": "CH"
	}, {
		"gender": "male",
		"name": {
			"title": "Mr",
			"first": "Robin",
			"last": "Charles"
		},
		"nat": "FR"
	}, {
		"gender": "male",
		"name": {
			"title": "Mr",
			"first": "Guy",
			"last": "Chapman"
		},
		"nat": "US"
	}, {
		"gender": "female",
		"name": {
			"title": "Mrs",
			"first": "Audrey",
			"last": "Newman"
		},
		"nat": "AU"
	}, {
		"gender": "male",
		"name": {
			"title": "Mr",
			"first": "Ege",
			"last": "Çankaya"
		},
		"nat": "TR"
	}, {
		"gender": "male",
		"name": {
			"title": "Mr",
			"first": "Nathaniel",
			"last": "Gibson"
		},
		"nat": "IE"
	}, {
		"gender": "male",
		"name": {
			"title": "Mr",
			"first": "Pedro",
			"last": "Cortes"
		},
		"nat": "ES"
	}, {
		"gender": "male",
		"name": {
			"title": "Mr",
			"first": "Volkan",
			"last": "Tuğluk"
		},
		"nat": "TR"
	}, {
		"gender": "male",
		"name": {
			"title": "Monsieur",
			"first": "Mustafa",
			"last": "Rey"
		},
		"nat": "CH"
	}, {
		"gender": "male",
		"name": {
			"title": "Mr",
			"first": "Murat",
			"last": "Karaduman"
		},
		"nat": "TR"
	}, {
		"gender": "female",
		"name": {
			"title": "Mrs",
			"first": "Melissa",
			"last": "Ruiz"
		},
		"nat": "US"
	}, {
		"gender": "female",
		"name": {
			"title": "Ms",
			"first": "Emilie",
			"last": "Mogen"
		},
		"nat": "NO"
	}, {
		"gender": "female",
		"name": {
			"title": "Ms",
			"first": "پارمیس",
			"last": "قاسمی"
		},
		"nat": "IR"
	}, {
		"gender": "male",
		"name": {
			"title": "Mr",
			"first": "Christos",
			"last": "Kocken"
		},
		"nat": "NL"
	}, {
		"gender": "male",
		"name": {
			"title": "Mr",
			"first": "Austin",
			"last": "Barrett"
		},
		"nat": "US"
	}, {
		"gender": "male",
		"name": {
			"title": "Mr",
			"first": "Tristan",
			"last": "Nymark"
		},
		"nat": "NO"
	}, {
		"gender": "female",
		"name": {
			"title": "Mademoiselle",
			"first": "Pauline",
			"last": "Martinez"
		},
		"nat": "CH"
	}, {
		"gender": "male",
		"name": {
			"title": "Mr",
			"first": "Hodota",
			"last": "Temnickiy"
		},
		"nat": "UA"
	}, {
		"gender": "male",
		"name": {
			"title": "Mr",
			"first": "Hunter",
			"last": "Lane"
		},
		"nat": "GB"
	}, {
		"gender": "female",
		"name": {
			"title": "Miss",
			"first": "Victoria",
			"last": "Thomsen"
		},
		"nat": "DK"
	}, {
		"gender": "female",
		"name": {
			"title": "Ms",
			"first": "یاسمن",
			"last": "موسوی"
		},
		"nat": "IR"
	}, {
		"gender": "female",
		"name": {
			"title": "Mrs",
			"first": "Oleksandra",
			"last": "Kanyuk"
		},
		"nat": "UA"
	}, {
		"gender": "female",
		"name": {
			"title": "Ms",
			"first": "رونیکا",
			"last": "رضایی"
		},
		"nat": "IR"
	}, {
		"gender": "male",
		"name": {
			"title": "Mr",
			"first": "Logan",
			"last": "Sullivan"
		},
		"nat": "AU"
	}, {
		"gender": "male",
		"name": {
			"title": "Mr",
			"first": "Gostyata",
			"last": "Baydak"
		},
		"nat": "UA"
	}, {
		"gender": "male",
		"name": {
			"title": "Mr",
			"first": "Steven",
			"last": "Williams"
		},
		"nat": "NO"
	}, {
		"gender": "female",
		"name": {
			"title": "Mrs",
			"first": "Ashley",
			"last": "Black"
		},
		"nat": "AU"
	}, {
		"gender": "male",
		"name": {
			"title": "Mr",
			"first": "Max",
			"last": "Mcdonalid"
		},
		"nat": "US"
	}, {
		"gender": "female",
		"name": {
			"title": "Mrs",
			"first": "Asunción",
			"last": "Velasco"
		},
		"nat": "ES"
	}, {
		"gender": "female",
		"name": {
			"title": "Mrs",
			"first": "Troyana",
			"last": "Trutovskiy"
		},
		"nat": "UA"
	}, {
		"gender": "female",
		"name": {
			"title": "Ms",
			"first": "Ceyhan",
			"last": "Öztonga"
		},
		"nat": "TR"
	}, {
		"gender": "male",
		"name": {
			"title": "Mr",
			"first": "Marshall",
			"last": "Holt"
		},
		"nat": "AU"
	}, {
		"gender": "male",
		"name": {
			"title": "Mr",
			"first": "Markus",
			"last": "Böse"
		},
		"nat": "DE"
	}, {
		"gender": "female",
		"name": {
			"title": "Miss",
			"first": "Julija",
			"last": "Perić"
		},
		"nat": "RS"
	}, {
		"gender": "male",
		"name": {
			"title": "Mr",
			"first": "Stanoje",
			"last": "Blagojević"
		},
		"nat": "RS"
	}, {
		"gender": "male",
		"name": {
			"title": "Mr",
			"first": "Noah",
			"last": "Jean-Baptiste"
		},
		"nat": "CA"
	}, {
		"gender": "male",
		"name": {
			"title": "Mr",
			"first": "Ethan",
			"last": "Jean-Baptiste"
		},
		"nat": "CA"
	}, {
		"gender": "male",
		"name": {
			"title": "Mr",
			"first": "Connor",
			"last": "Harris"
		},
		"nat": "NZ"
	}, {
		"gender": "female",
		"name": {
			"title": "Mrs",
			"first": "Vickie",
			"last": "Murphy"
		},
		"nat": "AU"
	}, {
		"gender": "female",
		"name": {
			"title": "Mrs",
			"first": "Rosa",
			"last": "Giménez"
		},
		"nat": "ES"
	}, {
		"gender": "female",
		"name": {
			"title": "Ms",
			"first": "Aada",
			"last": "Ramo"
		},
		"nat": "FI"
	}, {
		"gender": "female",
		"name": {
			"title": "Mrs",
			"first": "Safae",
			"last": "Schellevis"
		},
		"nat": "NL"
	}, {
		"gender": "male",
		"name": {
			"title": "Mr",
			"first": "Vedat",
			"last": "Demirbaş"
		},
		"nat": "TR"
	}, {
		"gender": "female",
		"name": {
			"title": "Mrs",
			"first": "Brandie",
			"last": "Marshall"
		},
		"nat": "US"
	}, {
		"gender": "male",
		"name": {
			"title": "Mr",
			"first": "Marlin",
			"last": "Speek"
		},
		"nat": "NL"
	}, {
		"gender": "male",
		"name": {
			"title": "Mr",
			"first": "علی رضا",
			"last": "سهيلي راد"
		},
		"nat": "IR"
	}, {
		"gender": "female",
		"name": {
			"title": "Mrs",
			"first": "Susanna",
			"last": "Pearson"
		},
		"nat": "IE"
	}, {
		"gender": "female",
		"name": {
			"title": "Mrs",
			"first": "Rosalia",
			"last": "Röser"
		},
		"nat": "DE"
	}, {
		"gender": "male",
		"name": {
			"title": "Mr",
			"first": "Alvar",
			"last": "Johnsen"
		},
		"nat": "NO"
	}, {
		"gender": "male",
		"name": {
			"title": "Mr",
			"first": "Malik",
			"last": "Taylor"
		},
		"nat": "CA"
	}, {
		"gender": "male",
		"name": {
			"title": "Mr",
			"first": "Daniel",
			"last": "Gil"
		},
		"nat": "ES"
	}, {
		"gender": "male",
		"name": {
			"title": "Mr",
			"first": "Fidélio",
			"last": "Nogueira"
		},
		"nat": "BR"
	}, {
		"gender": "female",
		"name": {
			"title": "Mrs",
			"first": "Frida",
			"last": "Hansen"
		},
		"nat": "DK"
	}, {
		"gender": "female",
		"name": {
			"title": "Mrs",
			"first": "Emily",
			"last": "Johansen"
		},
		"nat": "DK"
	}, {
		"gender": "female",
		"name": {
			"title": "Ms",
			"first": "Nicole",
			"last": "Wallace"
		},
		"nat": "US"
	}, {
		"gender": "male",
		"name": {
			"title": "Mr",
			"first": "Ryan",
			"last": "Williams"
		},
		"nat": "CA"
	}, {
		"gender": "female",
		"name": {
			"title": "Ms",
			"first": "Lycke",
			"last": "Isene"
		},
		"nat": "NO"
	}, {
		"gender": "female",
		"name": {
			"title": "Ms",
			"first": "Tone",
			"last": "Hjulstad"
		},
		"nat": "NO"
	}, {
		"gender": "female",
		"name": {
			"title": "Ms",
			"first": "Sonika",
			"last": "Moolya"
		},
		"nat": "IN"
	}, {
		"gender": "male",
		"name": {
			"title": "Mr",
			"first": "Flynn",
			"last": "Walker"
		},
		"nat": "NZ"
	}, {
		"gender": "male",
		"name": {
			"title": "Mr",
			"first": "Bojan",
			"last": "Vlot"
		},
		"nat": "NL"
	}, {
		"gender": "female",
		"name": {
			"title": "Ms",
			"first": "Ella",
			"last": "Martin"
		},
		"nat": "NZ"
	}, {
		"gender": "male",
		"name": {
			"title": "Mr",
			"first": "Zdravko",
			"last": "Mock"
		},
		"nat": "DE"
	}, {
		"gender": "male",
		"name": {
			"title": "Mr",
			"first": "Jayanth",
			"last": "Chavare"
		},
		"nat": "IN"
	}, {
		"gender": "female",
		"name": {
			"title": "Ms",
			"first": "مرسانا",
			"last": "قاسمی"
		},
		"nat": "IR"
	}, {
		"gender": "female",
		"name": {
			"title": "Miss",
			"first": "Tiffany",
			"last": "Butler"
		},
		"nat": "AU"
	}, {
		"gender": "female",
		"name": {
			"title": "Ms",
			"first": "Eva",
			"last": "Soto"
		},
		"nat": "IE"
	}, {
		"gender": "female",
		"name": {
			"title": "Miss",
			"first": "Alice",
			"last": "Williams"
		},
		"nat": "CA"
	}, {
		"gender": "male",
		"name": {
			"title": "Mr",
			"first": "Nathanaël",
			"last": "Leclerc"
		},
		"nat": "FR"
	}, {
		"gender": "male",
		"name": {
			"title": "Mr",
			"first": "Mustafa",
			"last": "Ulseth"
		},
		"nat": "NO"
	}, {
		"gender": "male",
		"name": {
			"title": "Mr",
			"first": "Marcos",
			"last": "Rosado"
		},
		"nat": "MX"
	}, {
		"gender": "female",
		"name": {
			"title": "Mrs",
			"first": "Jaqueline",
			"last": "Martínez"
		},
		"nat": "MX"
	}, {
		"gender": "male",
		"name": {
			"title": "Mr",
			"first": "Matéo",
			"last": "Schmitt"
		},
		"nat": "FR"
	}, {
		"gender": "female",
		"name": {
			"title": "Miss",
			"first": "Kitty",
			"last": "Wright"
		},
		"nat": "US"
	}, {
		"gender": "female",
		"name": {
			"title": "Mrs",
			"first": "Inna",
			"last": "Vaskiv"
		},
		"nat": "UA"
	}, {
		"gender": "female",
		"name": {
			"title": "Ms",
			"first": "Prithvi",
			"last": "Moolya"
		},
		"nat": "IN"
	}, {
		"gender": "male",
		"name": {
			"title": "Mr",
			"first": "Andrés",
			"last": "Santana"
		},
		"nat": "ES"
	}, {
		"gender": "male",
		"name": {
			"title": "Mr",
			"first": "Maximino",
			"last": "Caraballo"
		},
		"nat": "MX"
	}, {
		"gender": "female",
		"name": {
			"title": "Mrs",
			"first": "Sara",
			"last": "Jensen"
		},
		"nat": "DK"
	}, {
		"gender": "male",
		"name": {
			"title": "Mr",
			"first": "Gordon",
			"last": "George"
		},
		"nat": "IE"
	}, {
		"gender": "male",
		"name": {
			"title": "Mr",
			"first": "Livio",
			"last": "Girard"
		},
		"nat": "FR"
	}]